setup.cfg
setup.py
betago/__init__.py
betago/model.py
betago/processor.py
betago.egg-info/PKG-INFO
betago.egg-info/SOURCES.txt
betago.egg-info/dependency_links.txt
betago.egg-info/not-zip-safe
betago.egg-info/pbr.json
betago.egg-info/requires.txt
betago.egg-info/top_level.txt
betago/dataloader/__init__.py
betago/dataloader/base_processor.py
betago/dataloader/goboard.py
betago/dataloader/index_processor.py
betago/dataloader/sampling.py