Metadata-Version: 1.1
Name: betago
Version: 0.1
Summary: Create your own go bot from scratch. We are Lee Sedol!
Home-page: http://github.com/maxpumperla/betago
Author: Max Pumperla
Author-email: max.pumperla@googlemail.com
License: MIT
Download-URL: https://github.com/maxpumperla/betago/tarball/0.1
Platform: UNKNOWN
